{
  "data": {
    "pokemon": [
      {
        "name": "chesnaught-mega",
        "weight": 900,
        "height": 16,
        "exp_yield": null,
        "abilities": [],
        "types": [
          {
            "type": {
              "name": "grass"
            }
          },
          {
            "type": {
              "name": "fighting"
            }
          }
        ],
        "stats": [
          {
            "base_stat": 88,
            "stat": {
              "name": "hp"
            }
          },
          {
            "base_stat": 137,
            "stat": {
              "name": "attack"
            }
          },
          {
            "base_stat": 172,
            "stat": {
              "name": "defense"
            }
          },
          {
            "base_stat": 74,
            "stat": {
              "name": "special-attack"
            }
          },
          {
            "base_stat": 115,
            "stat": {
              "name": "special-defense"
            }
          },
          {
            "base_stat": 44,
            "stat": {
              "name": "speed"
            }
          }
        ],
        "levelUpMoves": [],
        "machineMoves": [],
        "eggMoves": [],
        "specy": {
          "specy_id": 652,
          "pokedex": [
            {
              "pokedex_number": 652
            }
          ],
          "gender_rate": 1,
          "category": [
            {
              "genus": "Spiny Armor Pokémon"
            }
          ],
          "evolution_chain": {
            "chain_id": 337,
            "species": [
              {
                "name": "chespin",
                "pre_evolution": null,
                "evolution_condition": []
              },
              {
                "name": "quilladin",
                "pre_evolution": 650,
                "evolution_condition": [
                  {
                    "evolutiontrigger": {
                      "name": "level-up"
                    },
                    "level": 16,
                    "happiness": null,
                    "item": null,
                    "held_item": null,
                    "time": ""
                  }
                ]
              },
              {
                "name": "chesnaught",
                "pre_evolution": 651,
                "evolution_condition": [
                  {
                    "evolutiontrigger": {
                      "name": "level-up"
                    },
                    "level": 36,
                    "happiness": null,
                    "item": null,
                    "held_item": null,
                    "time": ""
                  }
                ]
              }
            ]
          }
        }
      }
    ]
  }
}