{
  "data": {
    "pokemon": [
      {
        "name": "dottler",
        "weight": 195,
        "height": 4,
        "exp_yield": 117,
        "abilities": [
          {
            "ability": {
              "name": "swarm"
            }
          },
          {
            "ability": {
              "name": "compound-eyes"
            }
          },
          {
            "ability": {
              "name": "telepathy"
            }
          }
        ],
        "types": [
          {
            "type": {
              "name": "bug"
            }
          },
          {
            "type": {
              "name": "psychic"
            }
          }
        ],
        "stats": [
          {
            "base_stat": 50,
            "stat": {
              "name": "hp"
            }
          },
          {
            "base_stat": 35,
            "stat": {
              "name": "attack"
            }
          },
          {
            "base_stat": 80,
            "stat": {
              "name": "defense"
            }
          },
          {
            "base_stat": 50,
            "stat": {
              "name": "special-attack"
            }
          },
          {
            "base_stat": 90,
            "stat": {
              "name": "special-defense"
            }
          },
          {
            "base_stat": 30,
            "stat": {
              "name": "speed"
            }
          }
        ],
        "levelUpMoves": [
          {
            "version": {
              "name": "sword-shield"
            },
            "move": {
              "name": "confusion",
              "power": 50,
              "type": {
                "name": "psychic"
              },
              "category": {
                "name": "special"
              }
            },
            "level": 0
          },
          {
            "version": {
              "name": "sword-shield"
            },
            "move": {
              "name": "light-screen",
              "power": null,
              "type": {
                "name": "psychic"
              },
              "category": {
                "name": "status"
              }
            },
            "level": 0
          },
          {
            "version": {
              "name": "sword-shield"
            },
            "move": {
              "name": "reflect",
              "power": null,
              "type": {
                "name": "psychic"
              },
              "category": {
                "name": "status"
              }
            },
            "level": 0
          },
          {
            "version": {
              "name": "sword-shield"
            },
            "move": {
              "name": "confusion",
              "power": 50,
              "type": {
                "name": "psychic"
              },
              "category": {
                "name": "special"
              }
            },
            "level": 1
          },
          {
            "version": {
              "name": "sword-shield"
            },
            "move": {
              "name": "light-screen",
              "power": null,
              "type": {
                "name": "psychic"
              },
              "category": {
                "name": "status"
              }
            },
            "level": 1
          },
          {
            "version": {
              "name": "sword-shield"
            },
            "move": {
              "name": "reflect",
              "power": null,
              "type": {
                "name": "psychic"
              },
              "category": {
                "name": "status"
              }
            },
            "level": 1
          },
          {
            "version": {
              "name": "sword-shield"
            },
            "move": {
              "name": "struggle-bug",
              "power": 50,
              "type": {
                "name": "bug"
              },
              "category": {
                "name": "special"
              }
            },
            "level": 1
          }
        ],
        "machineMoves": [
          {
            "version": {
              "name": "sword-shield"
            },
            "move": {
              "name": "solar-beam",
              "power": 120,
              "type": {
                "name": "grass"
              },
              "category": {
                "name": "special"
              }
            }
          },
          {
            "version": {
              "name": "sword-shield"
            },
            "move": {
              "name": "psychic",
              "power": 90,
              "type": {
                "name": "psychic"
              },
              "category": {
                "name": "special"
              }
            }
          },
          {
            "version": {
              "name": "sword-shield"
            },
            "move": {
              "name": "light-screen",
              "power": null,
              "type": {
                "name": "psychic"
              },
              "category": {
                "name": "status"
              }
            }
          },
          {
            "version": {
              "name": "sword-shield"
            },
            "move": {
              "name": "reflect",
              "power": null,
              "type": {
                "name": "psychic"
              },
              "category": {
                "name": "status"
              }
            }
          },
          {
            "version": {
              "name": "sword-shield"
            },
            "move": {
              "name": "leech-life",
              "power": 80,
              "type": {
                "name": "bug"
              },
              "category": {
                "name": "physical"
              }
            }
          },
          {
            "version": {
              "name": "sword-shield"
            },
            "move": {
              "name": "rest",
              "power": null,
              "type": {
                "name": "psychic"
              },
              "category": {
                "name": "status"
              }
            }
          },
          {
            "version": {
              "name": "sword-shield"
            },
            "move": {
              "name": "substitute",
              "power": null,
              "type": {
                "name": "normal"
              },
              "category": {
                "name": "status"
              }
            }
          },
          {
            "version": {
              "name": "sword-shield"
            },
            "move": {
              "name": "snore",
              "power": 50,
              "type": {
                "name": "normal"
              },
              "category": {
                "name": "special"
              }
            }
          },
          {
            "version": {
              "name": "sword-shield"
            },
            "move": {
              "name": "protect",
              "power": null,
              "type": {
                "name": "normal"
              },
              "category": {
                "name": "status"
              }
            }
          },
          {
            "version": {
              "name": "sword-shield"
            },
            "move": {
              "name": "endure",
              "power": null,
              "type": {
                "name": "normal"
              },
              "category": {
                "name": "status"
              }
            }
          },
          {
            "version": {
              "name": "sword-shield"
            },
            "move": {
              "name": "attract",
              "power": null,
              "type": {
                "name": "normal"
              },
              "category": {
                "name": "status"
              }
            }
          },
          {
            "version": {
              "name": "sword-shield"
            },
            "move": {
              "name": "sleep-talk",
              "power": null,
              "type": {
                "name": "normal"
              },
              "category": {
                "name": "status"
              }
            }
          },
          {
            "version": {
              "name": "sword-shield"
            },
            "move": {
              "name": "safeguard",
              "power": null,
              "type": {
                "name": "normal"
              },
              "category": {
                "name": "status"
              }
            }
          },
          {
            "version": {
              "name": "sword-shield"
            },
            "move": {
              "name": "shadow-ball",
              "power": 80,
              "type": {
                "name": "ghost"
              },
              "category": {
                "name": "special"
              }
            }
          },
          {
            "version": {
              "name": "sword-shield"
            },
            "move": {
              "name": "future-sight",
              "power": 120,
              "type": {
                "name": "psychic"
              },
              "category": {
                "name": "special"
              }
            }
          },
          {
            "version": {
              "name": "sword-shield"
            },
            "move": {
              "name": "facade",
              "power": 70,
              "type": {
                "name": "normal"
              },
              "category": {
                "name": "physical"
              }
            }
          },
          {
            "version": {
              "name": "sword-shield"
            },
            "move": {
              "name": "helping-hand",
              "power": null,
              "type": {
                "name": "normal"
              },
              "category": {
                "name": "status"
              }
            }
          },
          {
            "version": {
              "name": "sword-shield"
            },
            "move": {
              "name": "trick",
              "power": null,
              "type": {
                "name": "psychic"
              },
              "category": {
                "name": "status"
              }
            }
          },
          {
            "version": {
              "name": "sword-shield"
            },
            "move": {
              "name": "skill-swap",
              "power": null,
              "type": {
                "name": "psychic"
              },
              "category": {
                "name": "status"
              }
            }
          },
          {
            "version": {
              "name": "sword-shield"
            },
            "move": {
              "name": "imprison",
              "power": null,
              "type": {
                "name": "psychic"
              },
              "category": {
                "name": "status"
              }
            }
          },
          {
            "version": {
              "name": "sword-shield"
            },
            "move": {
              "name": "iron-defense",
              "power": null,
              "type": {
                "name": "steel"
              },
              "category": {
                "name": "status"
              }
            }
          },
          {
            "version": {
              "name": "sword-shield"
            },
            "move": {
              "name": "calm-mind",
              "power": null,
              "type": {
                "name": "psychic"
              },
              "category": {
                "name": "status"
              }
            }
          },
          {
            "version": {
              "name": "sword-shield"
            },
            "move": {
              "name": "payback",
              "power": 50,
              "type": {
                "name": "dark"
              },
              "category": {
                "name": "physical"
              }
            }
          },
          {
            "version": {
              "name": "sword-shield"
            },
            "move": {
              "name": "power-swap",
              "power": null,
              "type": {
                "name": "psychic"
              },
              "category": {
                "name": "status"
              }
            }
          },
          {
            "version": {
              "name": "sword-shield"
            },
            "move": {
              "name": "guard-swap",
              "power": null,
              "type": {
                "name": "psychic"
              },
              "category": {
                "name": "status"
              }
            }
          },
          {
            "version": {
              "name": "sword-shield"
            },
            "move": {
              "name": "bug-buzz",
              "power": 90,
              "type": {
                "name": "bug"
              },
              "category": {
                "name": "special"
              }
            }
          },
          {
            "version": {
              "name": "sword-shield"
            },
            "move": {
              "name": "energy-ball",
              "power": 90,
              "type": {
                "name": "grass"
              },
              "category": {
                "name": "special"
              }
            }
          },
          {
            "version": {
              "name": "sword-shield"
            },
            "move": {
              "name": "zen-headbutt",
              "power": 80,
              "type": {
                "name": "psychic"
              },
              "category": {
                "name": "physical"
              }
            }
          },
          {
            "version": {
              "name": "sword-shield"
            },
            "move": {
              "name": "trick-room",
              "power": null,
              "type": {
                "name": "psychic"
              },
              "category": {
                "name": "status"
              }
            }
          },
          {
            "version": {
              "name": "sword-shield"
            },
            "move": {
              "name": "wonder-room",
              "power": null,
              "type": {
                "name": "psychic"
              },
              "category": {
                "name": "status"
              }
            }
          },
          {
            "version": {
              "name": "sword-shield"
            },
            "move": {
              "name": "psyshock",
              "power": 80,
              "type": {
                "name": "psychic"
              },
              "category": {
                "name": "special"
              }
            }
          },
          {
            "version": {
              "name": "sword-shield"
            },
            "move": {
              "name": "magic-room",
              "power": null,
              "type": {
                "name": "psychic"
              },
              "category": {
                "name": "status"
              }
            }
          },
          {
            "version": {
              "name": "sword-shield"
            },
            "move": {
              "name": "round",
              "power": 60,
              "type": {
                "name": "normal"
              },
              "category": {
                "name": "special"
              }
            }
          },
          {
            "version": {
              "name": "sword-shield"
            },
            "move": {
              "name": "stored-power",
              "power": 20,
              "type": {
                "name": "psychic"
              },
              "category": {
                "name": "special"
              }
            }
          },
          {
            "version": {
              "name": "sword-shield"
            },
            "move": {
              "name": "ally-switch",
              "power": null,
              "type": {
                "name": "psychic"
              },
              "category": {
                "name": "status"
              }
            }
          },
          {
            "version": {
              "name": "sword-shield"
            },
            "move": {
              "name": "psychic-terrain",
              "power": null,
              "type": {
                "name": "psychic"
              },
              "category": {
                "name": "status"
              }
            }
          },
          {
            "version": {
              "name": "sword-shield"
            },
            "move": {
              "name": "body-press",
              "power": 80,
              "type": {
                "name": "fighting"
              },
              "category": {
                "name": "physical"
              }
            }
          }
        ],
        "eggMoves": [
          {
            "version": {
              "name": "sword-shield"
            },
            "move": {
              "name": "expanding-force",
              "power": 80,
              "type": {
                "name": "psychic"
              },
              "category": {
                "name": "special"
              }
            }
          }
        ],
        "specy": {
          "specy_id": 825,
          "pokedex": [
            {
              "pokedex_number": 825
            }
          ],
          "gender_rate": 4,
          "category": [
            {
              "genus": "Radome Pokémon"
            }
          ],
          "evolution_chain": {
            "chain_id": 435,
            "species": [
              {
                "name": "blipbug",
                "pre_evolution": null,
                "evolution_condition": []
              },
              {
                "name": "dottler",
                "pre_evolution": 824,
                "evolution_condition": [
                  {
                    "evolutiontrigger": {
                      "name": "level-up"
                    },
                    "level": 10,
                    "happiness": null,
                    "item": null,
                    "held_item": null,
                    "time": ""
                  }
                ]
              },
              {
                "name": "orbeetle",
                "pre_evolution": 825,
                "evolution_condition": [
                  {
                    "evolutiontrigger": {
                      "name": "level-up"
                    },
                    "level": 30,
                    "happiness": null,
                    "item": null,
                    "held_item": null,
                    "time": ""
                  }
                ]
              }
            ]
          }
        }
      }
    ]
  }
}